{"repo_name": "ARM-software@lisa", "error_file": {"ARM-software@lisa/setup.py": [], "ARM-software@lisa/doc/test_example.py": [], "ARM-software@lisa/doc/conf.py": [], "ARM-software@lisa/tools/get_sd_flags.py": [], "ARM-software@lisa/tools/check-test-fix.py": [], "ARM-software@lisa/tools/for-each-subtree.py": [], "ARM-software@lisa/tools/env-list.py": [], "ARM-software@lisa/tools/wa_user_directory/plugins/ubsystemuijanktests/__init__.py": [], "ARM-software@lisa/tools/exekall/setup.py": [], "ARM-software@lisa/tools/exekall/exekall/_utils.py": [], "ARM-software@lisa/tools/exekall/exekall/__init__.py": [], "ARM-software@lisa/tools/exekall/exekall/engine.py": [], "ARM-software@lisa/tools/exekall/exekall/customization.py": [], "ARM-software@lisa/tools/exekall/exekall/valuedb.py": [], "ARM-software@lisa/tools/exekall/exekall/main.py": [], "ARM-software@lisa/tools/exekall/exekall/tests/suite.py": [], "ARM-software@lisa/tools/exekall/exekall/tests/utils.py": [], "ARM-software@lisa/tools/exekall/exekall/tests/exekall_customize.py": [], "ARM-software@lisa/tools/bisector/setup.py": [], "ARM-software@lisa/tools/bisector/bisector/bisector.py": [{"name": "__file__", "scope": "mod", "type": "unresolved", "path_id": [], "path_src": []}, {"name": "dump_results_dir", "scope": "mod.LISATestStep.report", "type": "unresolved", "path_id": [], "path_src": []}, {"name": "__file__", "scope": "mod.get_class", "type": "unresolved", "path_id": [], "path_src": []}, {"name": "__file__", "scope": "mod.MacroStep.get_step_src_files", "type": "unresolved", "path_id": [], "path_src": []}, {"name": "__file__", "scope": "mod.MacroStep.get_step_src_files", "type": "unresolved", "path_id": [], "path_src": []}, {"name": "pydbus", "scope": "mod.get_dbus_bus", "type": "foreign", "path_id": [], "path_src": []}, {"name": "GLib", "scope": "mod.dbus_variant", "type": "foreign", "path_id": [], "path_src": []}, {"name": "GLib", "scope": "mod.dbus_variant", "type": "foreign", "path_id": [], "path_src": []}, {"name": "GLib", "scope": "mod.dbus_variant", "type": "foreign", "path_id": [], "path_src": []}, {"name": "GLib", "scope": "mod.dbus_variant", "type": "foreign", "path_id": [], "path_src": []}, {"name": "GLib", "scope": "mod.dbus_variant", "type": "foreign", "path_id": [], "path_src": []}, {"name": "pydbus", "scope": "mod.DBusSlaveManager", "type": "foreign", "path_id": [], "path_src": []}, {"name": "GLib", "scope": "mod.DBusSlaveManager.publish", "type": "foreign", "path_id": [], "path_src": []}, {"name": "gi", "scope": "mod.DBusSlaveThread._thread_main", "type": "foreign", "path_id": [], "path_src": []}, {"name": "GLib", "scope": "mod.DBusSlaveThread._thread_main", "type": "foreign", "path_id": [], "path_src": []}, {"name": "GLib", "scope": "mod.DBusSlaveThread._thread_main", "type": "foreign", "path_id": [], "path_src": []}, {"name": "GLib", "scope": "mod.DBusSlaveThread._thread_main", "type": "foreign", "path_id": [], "path_src": []}, {"name": "GLib", "scope": "mod.DBusSlaveThread._thread_main", "type": "foreign", "path_id": [], "path_src": []}, {"name": "GLib", "scope": "mod.DBusSlaveThread._thread_main", "type": "foreign", "path_id": [], "path_src": []}, {"name": "GLib", "scope": "mod.DBusSlaveThread._thread_main", "type": "foreign", "path_id": [], "path_src": []}, {"name": "GLib", "scope": "mod.DBusSlaveThread._thread_main", "type": "foreign", "path_id": [], "path_src": []}, {"name": "GLib", "scope": "mod.send_cmd", "type": "foreign", "path_id": [], "path_src": []}, {"name": "GLib", "scope": "mod.do_monitor", "type": "foreign", "path_id": [], "path_src": []}, {"name": "GLib", "scope": "mod.do_monitor", "type": "foreign", "path_id": [], "path_src": []}, {"name": "GLib", "scope": "mod.do_monitor", "type": "foreign", "path_id": [], "path_src": []}, {"name": "GLib", "scope": "mod.do_monitor", "type": "foreign", "path_id": [], "path_src": []}, {"name": "GLib", "scope": "mod.do_monitor_server", "type": "foreign", "path_id": [], "path_src": []}, {"name": "GLib", "scope": "mod.DBusSlaveBook.__init__", "type": "foreign", "path_id": [], "path_src": []}, {"name": "GLib", "scope": "mod.DBusSlaveBook._request_bus_name", "type": "foreign", "path_id": [], "path_src": []}, {"name": "GLib", "scope": "mod.DBusSlaveBook.get_slave_manager", "type": "foreign", "path_id": [], "path_src": []}, {"name": "GLib", "scope": "mod.DBusSlaveBook.RegisterSlave", "type": "foreign", "path_id": [], "path_src": []}], "ARM-software@lisa/external/devlib/setup.py": [{"name": "__file__", "scope": "mod", "type": "unresolved", "path_id": [], "path_src": []}, {"name": "__file__", "scope": "mod", "type": "unresolved", "path_id": [], "path_src": []}, {"name": "package_name", "scope": "mod", "type": "local", "path_id": [], "path_src": []}, {"name": "package_dir", "scope": "mod", "type": "local", "path_id": [], "path_src": []}], "ARM-software@lisa/external/devlib/doc/conf.py": [], "ARM-software@lisa/external/devlib/devlib/target.py": [], "ARM-software@lisa/external/devlib/devlib/__init__.py": [], "ARM-software@lisa/external/devlib/devlib/host.py": [{"name": "__file__", "scope": "mod", "type": "unresolved", "path_id": [], "path_src": []}], "ARM-software@lisa/external/devlib/devlib/exception.py": [], "ARM-software@lisa/external/devlib/devlib/connection.py": [], "ARM-software@lisa/external/devlib/devlib/collector/__init__.py": [], "ARM-software@lisa/external/devlib/devlib/collector/systrace.py": [], "ARM-software@lisa/external/devlib/devlib/collector/logcat.py": [], "ARM-software@lisa/external/devlib/devlib/collector/dmesg.py": [], "ARM-software@lisa/external/devlib/devlib/collector/ftrace.py": [], "ARM-software@lisa/external/devlib/devlib/collector/serial_trace.py": [], "ARM-software@lisa/external/devlib/devlib/collector/perf.py": [], "ARM-software@lisa/external/devlib/devlib/collector/screencapture.py": [], "ARM-software@lisa/external/devlib/devlib/platform/__init__.py": [], "ARM-software@lisa/external/devlib/devlib/platform/gem5.py": [{"name": "gem5_logger", "scope": "mod.Gem5SimulationPlatform.gem5_capture_screen", "type": "unresolved", "path_id": [], "path_src": []}], "ARM-software@lisa/external/devlib/devlib/platform/arm.py": [], "ARM-software@lisa/external/devlib/devlib/derived/__init__.py": [], "ARM-software@lisa/external/devlib/devlib/derived/energy.py": [], "ARM-software@lisa/external/devlib/devlib/derived/fps.py": [], "ARM-software@lisa/external/devlib/devlib/module/__init__.py": [], "ARM-software@lisa/external/devlib/devlib/module/devfreq.py": [], "ARM-software@lisa/external/devlib/devlib/module/cooling.py": [], "ARM-software@lisa/external/devlib/devlib/module/cpuidle.py": [], "ARM-software@lisa/external/devlib/devlib/module/hotplug.py": [], "ARM-software@lisa/external/devlib/devlib/module/cpufreq.py": [], "ARM-software@lisa/external/devlib/devlib/module/vexpress.py": [], "ARM-software@lisa/external/devlib/devlib/module/sched.py": [], "ARM-software@lisa/external/devlib/devlib/module/thermal.py": [], "ARM-software@lisa/external/devlib/devlib/module/gem5stats.py": [], "ARM-software@lisa/external/devlib/devlib/module/gpufreq.py": [], "ARM-software@lisa/external/devlib/devlib/module/hwmon.py": [], "ARM-software@lisa/external/devlib/devlib/module/android.py": [], "ARM-software@lisa/external/devlib/devlib/module/biglittle.py": [], "ARM-software@lisa/external/devlib/devlib/utils/parse_aep.py": [], "ARM-software@lisa/external/devlib/devlib/utils/__init__.py": [], "ARM-software@lisa/external/devlib/devlib/utils/serial_port.py": [], "ARM-software@lisa/external/devlib/devlib/utils/types.py": [], "ARM-software@lisa/external/devlib/devlib/utils/rendering.py": [], "ARM-software@lisa/external/devlib/devlib/utils/ssh.py": [{"name": "attempts", "scope": "mod.Gem5Connection.wait_for_device", "type": "unresolved", "path_id": [], "path_src": []}], "ARM-software@lisa/external/devlib/devlib/utils/csvutil.py": [], "ARM-software@lisa/external/devlib/devlib/utils/version.py": [{"name": "__file__", "scope": "mod.get_commit", "type": "unresolved", "path_id": [], "path_src": []}], "ARM-software@lisa/external/devlib/devlib/utils/gem5.py": [], "ARM-software@lisa/external/devlib/devlib/utils/uefi.py": [], "ARM-software@lisa/external/devlib/devlib/utils/misc.py": [], "ARM-software@lisa/external/devlib/devlib/utils/android.py": [], "ARM-software@lisa/external/devlib/devlib/utils/uboot.py": [], "ARM-software@lisa/external/devlib/devlib/instrument/arm_energy_probe.py": [], "ARM-software@lisa/external/devlib/devlib/instrument/__init__.py": [], "ARM-software@lisa/external/devlib/devlib/instrument/monsoon.py": [], "ARM-software@lisa/external/devlib/devlib/instrument/acmecape.py": [], "ARM-software@lisa/external/devlib/devlib/instrument/daq.py": [{"name": "import_error_mesg", "scope": "mod.DaqInstrument.__init__", "type": "foreign", "path_id": [], "path_src": []}], "ARM-software@lisa/external/devlib/devlib/instrument/energy_probe.py": [], "ARM-software@lisa/external/devlib/devlib/instrument/gem5power.py": [], "ARM-software@lisa/external/devlib/devlib/instrument/frames.py": [], "ARM-software@lisa/external/devlib/devlib/instrument/hwmon.py": [], "ARM-software@lisa/external/devlib/devlib/instrument/baylibre_acme.py": [{"name": "iio_import_error", "scope": "mod.BaylibreAcmeInstrument.__init__", "type": "foreign", "path_id": [], "path_src": []}, {"name": "iio", "scope": "mod.BaylibreAcmeInstrument.__init__", "type": "foreign", "path_id": [], "path_src": []}, {"name": "iio", "scope": "mod.BaylibreAcmeInstrument.check_version", "type": "foreign", "path_id": [], "path_src": []}, {"name": "iio", "scope": "mod.BaylibreAcmeInstrument.check_version", "type": "foreign", "path_id": [], "path_src": []}, {"name": "iio_import_error", "scope": "mod.BaylibreAcmeLocalInstrument.__init__", "type": "foreign", "path_id": [], "path_src": []}, {"name": "iio", "scope": "mod.BaylibreAcmeLocalInstrument.__init__", "type": "foreign", "path_id": [], "path_src": []}, {"name": "iio_import_error", "scope": "mod.BaylibreAcmeXMLInstrument.__init__", "type": "foreign", "path_id": [], "path_src": []}, {"name": "iio", "scope": "mod.BaylibreAcmeXMLInstrument.__init__", "type": "foreign", "path_id": [], "path_src": []}, {"name": "iio_import_error", "scope": "mod.BaylibreAcmeNetworkInstrument.__init__", "type": "foreign", "path_id": [], "path_src": []}, {"name": "iio", "scope": "mod.BaylibreAcmeNetworkInstrument.__init__", "type": "foreign", "path_id": [], "path_src": []}], "ARM-software@lisa/external/devlib/devlib/instrument/netstats/__init__.py": [{"name": "__file__", "scope": "mod", "type": "unresolved", "path_id": [], "path_src": []}], "ARM-software@lisa/external/devlib/tests/test_target.py": [], "ARM-software@lisa/external/workload-automation/setup.py": [{"name": "__file__", "scope": "mod", "type": "unresolved", "path_id": [], "path_src": []}, {"name": "__file__", "scope": "mod", "type": "unresolved", "path_id": [], "path_src": []}, {"name": "package_name", "scope": "mod", "type": "local", "path_id": [], "path_src": []}, {"name": "package_dir", "scope": "mod", "type": "local", "path_id": [], "path_src": []}], "ARM-software@lisa/external/workload-automation/doc/build_plugin_docs.py": [], "ARM-software@lisa/external/workload-automation/doc/build_instrument_method_map.py": [{"name": "__file__", "scope": "mod", "type": "unresolved", "path_id": [], "path_src": []}], "ARM-software@lisa/external/workload-automation/doc/source/conf.py": [{"name": "__file__", "scope": "mod", "type": "unresolved", "path_id": [], "path_src": []}, {"name": "__file__", "scope": "mod.setup", "type": "unresolved", "path_id": [], "path_src": []}], "ARM-software@lisa/external/workload-automation/wa/__init__.py": [], "ARM-software@lisa/external/workload-automation/wa/commands/__init__.py": [], "ARM-software@lisa/external/workload-automation/wa/commands/list.py": [], "ARM-software@lisa/external/workload-automation/wa/commands/run.py": [], "ARM-software@lisa/external/workload-automation/wa/commands/report.py": [], "ARM-software@lisa/external/workload-automation/wa/commands/create.py": [{"name": "__file__", "scope": "mod", "type": "unresolved", "path_id": [], "path_src": []}, {"name": "OperationalError", "scope": "mod.CreateDatabaseSubcommand.execute", "type": "foreign", "path_id": [], "path_src": []}, {"name": "connect", "scope": "mod.CreateDatabaseSubcommand._validate_version", "type": "foreign", "path_id": [], "path_src": []}, {"name": "connect", "scope": "mod.CreateDatabaseSubcommand._get_database_schema_version", "type": "foreign", "path_id": [], "path_src": []}, {"name": "OperationalError", "scope": "mod.CreateDatabaseSubcommand._check_database_existence", "type": "foreign", "path_id": [], "path_src": []}, {"name": "connect", "scope": "mod.CreateDatabaseSubcommand._check_database_existence", "type": "foreign", "path_id": [], "path_src": []}, {"name": "connect", "scope": "mod.CreateDatabaseSubcommand._create_database_postgres", "type": "foreign", "path_id": [], "path_src": []}, {"name": "ISOLATION_LEVEL_AUTOCOMMIT", "scope": "mod.CreateDatabaseSubcommand._create_database_postgres", "type": "foreign", "path_id": [], "path_src": []}, {"name": "connect", "scope": "mod.CreateDatabaseSubcommand._apply_database_schema", "type": "foreign", "path_id": [], "path_src": []}, {"name": "extras", "scope": "mod.CreateDatabaseSubcommand._apply_database_schema", "type": "foreign", "path_id": [], "path_src": []}], "ARM-software@lisa/external/workload-automation/wa/commands/process.py": [], "ARM-software@lisa/external/workload-automation/wa/commands/revent.py": [{"name": "raw_input", "scope": "mod.RecordCommand.record", "type": "foreign", "path_id": [], "path_src": []}, {"name": "raw_input", "scope": "mod.RecordCommand.record", "type": "foreign", "path_id": [], "path_src": []}], "ARM-software@lisa/external/workload-automation/wa/commands/show.py": [], "ARM-software@lisa/external/workload-automation/wa/instruments/__init__.py": [], "ARM-software@lisa/external/workload-automation/wa/instruments/screencap.py": [], "ARM-software@lisa/external/workload-automation/wa/instruments/serialmon.py": [], "ARM-software@lisa/external/workload-automation/wa/instruments/dmesg.py": [], "ARM-software@lisa/external/workload-automation/wa/instruments/trace_cmd.py": [], "ARM-software@lisa/external/workload-automation/wa/instruments/fps.py": [], "ARM-software@lisa/external/workload-automation/wa/instruments/perf.py": [], "ARM-software@lisa/external/workload-automation/wa/instruments/hwmon.py": [], "ARM-software@lisa/external/workload-automation/wa/instruments/misc.py": [], "ARM-software@lisa/external/workload-automation/wa/instruments/delay.py": [], "ARM-software@lisa/external/workload-automation/wa/instruments/energy_measurement.py": [], "ARM-software@lisa/external/workload-automation/wa/instruments/poller/__init__.py": [], "ARM-software@lisa/external/workload-automation/wa/instruments/proc_stat/__init__.py": [], "ARM-software@lisa/external/workload-automation/wa/output_processors/status.py": [], "ARM-software@lisa/external/workload-automation/wa/output_processors/__init__.py": [], "ARM-software@lisa/external/workload-automation/wa/output_processors/csvproc.py": [], "ARM-software@lisa/external/workload-automation/wa/output_processors/targz.py": [], "ARM-software@lisa/external/workload-automation/wa/output_processors/uxperf.py": [], "ARM-software@lisa/external/workload-automation/wa/output_processors/sqlite.py": [], "ARM-software@lisa/external/workload-automation/wa/output_processors/postgresql.py": [{"name": "import_error_msg", "scope": "mod.PostgresqlResultProcessor.initialize", "type": "foreign", "path_id": [], "path_src": []}, {"name": "extras", "scope": "mod.PostgresqlResultProcessor.initialize", "type": "foreign", "path_id": [], "path_src": []}, {"name": "extras", "scope": "mod.PostgresqlResultProcessor.initialize", "type": "foreign", "path_id": [], "path_src": []}, {"name": "extras", "scope": "mod.PostgresqlResultProcessor.initialize", "type": "foreign", "path_id": [], "path_src": []}, {"name": "Psycopg2Error", "scope": "mod.PostgresqlResultProcessor.connect_to_database", "type": "foreign", "path_id": [], "path_src": []}, {"name": "connect", "scope": "mod.PostgresqlResultProcessor.connect_to_database", "type": "foreign", "path_id": [], "path_src": []}], "ARM-software@lisa/external/workload-automation/wa/output_processors/cpustates.py": [], "ARM-software@lisa/external/workload-automation/wa/framework/output_processor.py": [], "ARM-software@lisa/external/workload-automation/wa/framework/entrypoint.py": [], "ARM-software@lisa/external/workload-automation/wa/framework/__init__.py": [], "ARM-software@lisa/external/workload-automation/wa/framework/run.py": [], "ARM-software@lisa/external/workload-automation/wa/framework/execution.py": [], "ARM-software@lisa/external/workload-automation/wa/framework/output.py": [], "ARM-software@lisa/external/workload-automation/wa/framework/version.py": [{"name": "__file__", "scope": "mod.get_commit", "type": "unresolved", "path_id": [], "path_src": []}], "ARM-software@lisa/external/workload-automation/wa/framework/host.py": [], "ARM-software@lisa/external/workload-automation/wa/framework/getters.py": [], "ARM-software@lisa/external/workload-automation/wa/framework/instrument.py": [], "ARM-software@lisa/external/workload-automation/wa/framework/exception.py": [], "ARM-software@lisa/external/workload-automation/wa/framework/pluginloader.py": [], "ARM-software@lisa/external/workload-automation/wa/framework/resource.py": [], "ARM-software@lisa/external/workload-automation/wa/framework/plugin.py": [], "ARM-software@lisa/external/workload-automation/wa/framework/workload.py": [], "ARM-software@lisa/external/workload-automation/wa/framework/signal.py": [], "ARM-software@lisa/external/workload-automation/wa/framework/job.py": [], "ARM-software@lisa/external/workload-automation/wa/framework/command.py": [], "ARM-software@lisa/external/workload-automation/wa/framework/target/assistant.py": [], "ARM-software@lisa/external/workload-automation/wa/framework/target/__init__.py": [], "ARM-software@lisa/external/workload-automation/wa/framework/target/runtime_parameter_manager.py": [], "ARM-software@lisa/external/workload-automation/wa/framework/target/config.py": [], "ARM-software@lisa/external/workload-automation/wa/framework/target/descriptor.py": [], "ARM-software@lisa/external/workload-automation/wa/framework/target/runtime_config.py": [], "ARM-software@lisa/external/workload-automation/wa/framework/target/manager.py": [], "ARM-software@lisa/external/workload-automation/wa/framework/target/info.py": [], "ARM-software@lisa/external/workload-automation/wa/framework/configuration/__init__.py": [], "ARM-software@lisa/external/workload-automation/wa/framework/configuration/tree.py": [], "ARM-software@lisa/external/workload-automation/wa/framework/configuration/execution.py": [], "ARM-software@lisa/external/workload-automation/wa/framework/configuration/core.py": [], "ARM-software@lisa/external/workload-automation/wa/framework/configuration/plugin_cache.py": [], "ARM-software@lisa/external/workload-automation/wa/framework/configuration/parsers.py": [], "ARM-software@lisa/external/workload-automation/wa/framework/configuration/default.py": [], "ARM-software@lisa/external/workload-automation/wa/utils/__init__.py": [], "ARM-software@lisa/external/workload-automation/wa/utils/postgres.py": [{"name": "__file__", "scope": "mod", "type": "unresolved", "path_id": [], "path_src": []}], "ARM-software@lisa/external/workload-automation/wa/utils/types.py": [{"name": "basestring", "scope": "mod.level.__eq__", "type": "foreign", "path_id": [], "path_src": []}, {"name": "basestring", "scope": "mod.level.__lt__", "type": "foreign", "path_id": [], "path_src": []}, {"name": "basestring", "scope": "mod.level.__ne__", "type": "foreign", "path_id": [], "path_src": []}, {"name": "long", "scope": "mod.ParameterDict._get_prefix", "type": "foreign", "path_id": [], "path_src": []}], "ARM-software@lisa/external/workload-automation/wa/utils/serializer.py": [], "ARM-software@lisa/external/workload-automation/wa/utils/terminalsize.py": [], "ARM-software@lisa/external/workload-automation/wa/utils/log.py": [], "ARM-software@lisa/external/workload-automation/wa/utils/formatter.py": [], "ARM-software@lisa/external/workload-automation/wa/utils/trace_cmd.py": [], "ARM-software@lisa/external/workload-automation/wa/utils/revent.py": [], "ARM-software@lisa/external/workload-automation/wa/utils/diff.py": [], "ARM-software@lisa/external/workload-automation/wa/utils/exec_control.py": [], "ARM-software@lisa/external/workload-automation/wa/utils/misc.py": [], "ARM-software@lisa/external/workload-automation/wa/utils/doc.py": [], "ARM-software@lisa/external/workload-automation/wa/utils/android.py": [], "ARM-software@lisa/external/workload-automation/wa/utils/cpustates.py": [], "ARM-software@lisa/external/workload-automation/wa/workloads/__init__.py": [], "ARM-software@lisa/external/workload-automation/wa/workloads/apache.py": [], "ARM-software@lisa/external/workload-automation/wa/workloads/idle.py": [], "ARM-software@lisa/external/workload-automation/wa/workloads/hackbench/__init__.py": [], "ARM-software@lisa/external/workload-automation/wa/workloads/deepbench/__init__.py": [], "ARM-software@lisa/external/workload-automation/wa/workloads/applaunch/__init__.py": [], "ARM-software@lisa/external/workload-automation/wa/workloads/homescreen/__init__.py": [], "ARM-software@lisa/external/workload-automation/wa/workloads/uibenchjanktests/__init__.py": [], "ARM-software@lisa/external/workload-automation/wa/workloads/motionmark/__init__.py": [], "ARM-software@lisa/external/workload-automation/wa/workloads/mongoperf/__init__.py": [], "ARM-software@lisa/external/workload-automation/wa/workloads/dhrystone/__init__.py": [], "ARM-software@lisa/external/workload-automation/wa/workloads/antutu/__init__.py": [], "ARM-software@lisa/external/workload-automation/wa/workloads/sysbench/__init__.py": [], "ARM-software@lisa/external/workload-automation/wa/workloads/rt_app/__init__.py": [{"name": "__file__", "scope": "mod", "type": "unresolved", "path_id": [], "path_src": []}], "ARM-software@lisa/external/workload-automation/wa/workloads/geekbench/__init__.py": [], "ARM-software@lisa/external/workload-automation/wa/workloads/hwuitest/__init__.py": [], "ARM-software@lisa/external/workload-automation/wa/workloads/gmail/__init__.py": [], "ARM-software@lisa/external/workload-automation/wa/workloads/vellamo/__init__.py": [], "ARM-software@lisa/external/workload-automation/wa/workloads/chrome/__init__.py": [], "ARM-software@lisa/external/workload-automation/wa/workloads/recentfling/__init__.py": [], "ARM-software@lisa/external/workload-automation/wa/workloads/adobereader/__init__.py": [], "ARM-software@lisa/external/workload-automation/wa/workloads/openssl/__init__.py": [], "ARM-software@lisa/external/workload-automation/wa/workloads/lmbench/__init__.py": [], "ARM-software@lisa/external/workload-automation/wa/workloads/angrybirds_rio/__init__.py": [], "ARM-software@lisa/external/workload-automation/wa/workloads/the_chase/__init__.py": [], "ARM-software@lisa/external/workload-automation/wa/workloads/googlephotos/__init__.py": [], "ARM-software@lisa/external/workload-automation/wa/workloads/pcmark/__init__.py": [], "ARM-software@lisa/external/workload-automation/wa/workloads/exoplayer/__init__.py": [], "ARM-software@lisa/external/workload-automation/wa/workloads/gfxbench/__init__.py": [], "ARM-software@lisa/external/workload-automation/wa/workloads/googleslides/__init__.py": [], "ARM-software@lisa/external/workload-automation/wa/workloads/androbench/__init__.py": [], "ARM-software@lisa/external/workload-automation/wa/workloads/jankbench/__init__.py": [], "ARM-software@lisa/external/workload-automation/wa/workloads/googleplaybooks/__init__.py": [], "ARM-software@lisa/external/workload-automation/wa/workloads/youtube_playback/__init__.py": [], "ARM-software@lisa/external/workload-automation/wa/workloads/stress_ng/__init__.py": [], "ARM-software@lisa/external/workload-automation/wa/workloads/youtube/__init__.py": [], "ARM-software@lisa/external/workload-automation/wa/workloads/memcpy/__init__.py": [{"name": "__file__", "scope": "mod", "type": "unresolved", "path_id": [], "path_src": []}], "ARM-software@lisa/external/workload-automation/wa/workloads/googlemaps/__init__.py": [], "ARM-software@lisa/external/workload-automation/wa/workloads/speedometer/__init__.py": [], "ARM-software@lisa/external/workload-automation/wa/workloads/manual/__init__.py": [], "ARM-software@lisa/external/workload-automation/wa/workloads/aitutu/__init__.py": [], "ARM-software@lisa/external/workload-automation/wa/workloads/glbenchmark/__init__.py": [], "ARM-software@lisa/external/workload-automation/wa/workloads/templerun2/__init__.py": [], "ARM-software@lisa/external/workload-automation/wa/workloads/meabo/__init__.py": [], "ARM-software@lisa/external/workload-automation/wa/workloads/shellscript/__init__.py": [], "ARM-software@lisa/external/workload-automation/wa/workloads/uibench/__init__.py": [], "ARM-software@lisa/external/workload-automation/wa/workloads/benchmarkpi/__init__.py": [], "ARM-software@lisa/external/workload-automation/dev_scripts/pylint_plugins.py": [], "ARM-software@lisa/external/workload-automation/tests/__init__.py": [], "ARM-software@lisa/external/workload-automation/tests/test_execution.py": [], "ARM-software@lisa/external/workload-automation/tests/test_diff.py": [{"name": "__file__", "scope": "mod.InterruptDiffTest.test_interrupt_diff", "type": "unresolved", "path_id": [], "path_src": []}], "ARM-software@lisa/external/workload-automation/tests/test_runtime_param_utils.py": [], "ARM-software@lisa/external/workload-automation/tests/test_plugin.py": [{"name": "__file__", "scope": "mod", "type": "unresolved", "path_id": [], "path_src": []}], "ARM-software@lisa/external/workload-automation/tests/test_exec_control.py": [], "ARM-software@lisa/external/workload-automation/tests/test_utils.py": [], "ARM-software@lisa/external/workload-automation/tests/test_config.py": [], "ARM-software@lisa/external/workload-automation/tests/test_signal.py": [], "ARM-software@lisa/external/workload-automation/tests/test_agenda_parser.py": [{"name": "__file__", "scope": "mod", "type": "unresolved", "path_id": [], "path_src": []}], "ARM-software@lisa/external/workload-automation/tests/data/test-config.py": [], "ARM-software@lisa/external/workload-automation/tests/data/extensions/devices/test_device.py": [], "ARM-software@lisa/lisa/target.py": [], "ARM-software@lisa/lisa/trace.py": [], "ARM-software@lisa/lisa/test_example.py": [], "ARM-software@lisa/lisa/__init__.py": [], "ARM-software@lisa/lisa/target_script.py": [], "ARM-software@lisa/lisa/datautils.py": [], "ARM-software@lisa/lisa/conf.py": [], "ARM-software@lisa/lisa/stats.py": [], "ARM-software@lisa/lisa/wa_results_collector.py": [{"name": "artifact_name", "scope": "mod.WaResultsCollector._read_energy_instrument_metrics", "type": "unresolved", "path_id": [], "path_src": []}], "ARM-software@lisa/lisa/_generic.py": [], "ARM-software@lisa/lisa/_typeclass.py": [], "ARM-software@lisa/lisa/version.py": [], "ARM-software@lisa/lisa/energy_meter.py": [], "ARM-software@lisa/lisa/wa.py": [], "ARM-software@lisa/lisa/utils.py": [{"name": "__file__", "scope": "mod.get_call_site", "type": "unresolved", "path_id": [], "path_src": []}, {"name": "__IPYTHON__", "scope": "mod.is_running_ipython", "type": "unresolved", "path_id": [], "path_src": []}, {"name": "sphobjinv", "scope": "mod._get_doc_url", "type": "foreign", "path_id": [], "path_src": []}, {"name": "IFrame", "scope": "mod.show_doc", "type": "foreign", "path_id": [], "path_src": []}], "ARM-software@lisa/lisa/regression.py": [], "ARM-software@lisa/lisa/exekall_customize.py": [], "ARM-software@lisa/lisa/pelt.py": [], "ARM-software@lisa/lisa/_git.py": [], "ARM-software@lisa/lisa/notebook.py": [], "ARM-software@lisa/lisa/energy_model.py": [], "ARM-software@lisa/lisa/wlgen/__init__.py": [], "ARM-software@lisa/lisa/wlgen/rta.py": [{"name": "other", "scope": "mod._SingleWloadBase.__and__", "type": "unresolved", "path_id": [], "path_src": []}, {"name": "other", "scope": "mod._SingleWloadBase.__and__", "type": "unresolved", "path_id": [], "path_src": []}], "ARM-software@lisa/lisa/wlgen/sysbench.py": [], "ARM-software@lisa/lisa/wlgen/workload.py": [], "ARM-software@lisa/lisa/platforms/platinfo.py": [], "ARM-software@lisa/lisa/platforms/hikey620.py": [], "ARM-software@lisa/lisa/platforms/juno_r0.py": [], "ARM-software@lisa/lisa/_cli_tools/__init__.py": [], "ARM-software@lisa/lisa/_cli_tools/lisa_conf_cat.py": [], "ARM-software@lisa/lisa/_cli_tools/lisa_platinfo_extract.py": [], "ARM-software@lisa/lisa/_cli_tools/lisa_plot.py": [], "ARM-software@lisa/lisa/_doc/manconf.py": [], "ARM-software@lisa/lisa/_doc/helpers.py": [], "ARM-software@lisa/lisa/_assets/__init__.py": [{"name": "__file__", "scope": "mod", "type": "unresolved", "path_id": [], "path_src": []}], "ARM-software@lisa/lisa/analysis/status.py": [], "ARM-software@lisa/lisa/analysis/__init__.py": [{"name": "__path__", "scope": "mod._import_submodules", "type": "unresolved", "path_id": [], "path_src": []}], "ARM-software@lisa/lisa/analysis/frequency.py": [], "ARM-software@lisa/lisa/analysis/base.py": [], "ARM-software@lisa/lisa/analysis/rta.py": [], "ARM-software@lisa/lisa/analysis/_proxy.py": [], "ARM-software@lisa/lisa/analysis/load_tracking.py": [], "ARM-software@lisa/lisa/analysis/thermal.py": [], "ARM-software@lisa/lisa/analysis/tasks.py": [{"name": "offset", "scope": "mod.TasksAnalysis.plot_tasks_activation", "type": "unresolved", "path_id": [], "path_src": []}], "ARM-software@lisa/lisa/analysis/functions.py": [{"name": "e", "scope": "mod.FunctionsAnalysis._df_with_ksym", "type": "unresolved", "path_id": [], "path_src": []}, {"name": "title", "scope": "mod.JSONStatsFunctionsAnalysis.plot_profiling_stats.plot_metric", "type": "unresolved", "path_id": [], "path_src": []}], "ARM-software@lisa/lisa/analysis/notebook.py": [], "ARM-software@lisa/lisa/analysis/cpus.py": [], "ARM-software@lisa/lisa/analysis/idle.py": [], "ARM-software@lisa/lisa/analysis/latency.py": [], "ARM-software@lisa/lisa/tests/__init__.py": [], "ARM-software@lisa/lisa/tests/hotplug.py": [{"name": "target_alive", "scope": "mod.HotplugBase._from_target", "type": "unresolved", "path_id": [], "path_src": []}, {"name": "target_alive", "scope": "mod.HotplugBase._from_target", "type": "unresolved", "path_id": [], "path_src": []}], "ARM-software@lisa/lisa/tests/base.py": [], "ARM-software@lisa/lisa/tests/cpufreq/sanity.py": [], "ARM-software@lisa/lisa/tests/scheduler/util_tracking.py": [], "ARM-software@lisa/lisa/tests/scheduler/__init__.py": [], "ARM-software@lisa/lisa/tests/scheduler/eas_behaviour.py": [], "ARM-software@lisa/lisa/tests/scheduler/sched_android.py": [], "ARM-software@lisa/lisa/tests/scheduler/misfit.py": [], "ARM-software@lisa/lisa/tests/scheduler/load_tracking.py": [], "ARM-software@lisa/lisa/tests/scheduler/sanity.py": [], "ARM-software@lisa/lisa/tests/staging/utilclamp.py": [{"name": "capa", "scope": "mod.UtilClamp._collect_capacities_flatten", "type": "unresolved", "path_id": [], "path_src": []}], "ARM-software@lisa/lisa/tests/staging/schedutil.py": [], "ARM-software@lisa/lisa/tests/staging/numa_behaviour.py": [], "ARM-software@lisa/tests/__init__.py": [], "ARM-software@lisa/tests/test_trace.py": [], "ARM-software@lisa/tests/test_conf.py": [], "ARM-software@lisa/tests/wlgen.py": [], "ARM-software@lisa/tests/test_test_bundle.py": [], "ARM-software@lisa/tests/utils.py": [{"name": "__file__", "scope": "mod", "type": "unresolved", "path_id": [], "path_src": []}], "ARM-software@lisa/tests/test_wlgen_rtapp.py": [], "ARM-software@lisa/tests/test_events_checkers.py": [], "ARM-software@lisa/tests/test_target.py": [], "ARM-software@lisa/tests/test_datautils.py": [], "ARM-software@lisa/tests/test_energy_model.py": []}}