{"repo_name": "GlebMorgan@PyUtils", "error_file": {"GlebMorgan@PyUtils/setup.py": [], "GlebMorgan@PyUtils/utils/bits.py": [{"name": "Ellipsis", "scope": "mod.Bits.extract", "type": "unresolved", "path_id": [], "path_src": []}, {"name": "Ellipsis", "scope": "mod.Bits.extract", "type": "unresolved", "path_id": [], "path_src": []}], "GlebMorgan@PyUtils/exps/readme_updater.py": [], "GlebMorgan@PyUtils/exps/filters.py": [], "GlebMorgan@PyUtils/tests/test_bits.py": [], "GlebMorgan@PyUtils/tests/benchmarks.py": []}}